permittivitycalc/__init__.py
permittivitycalc/helper_functions.py
permittivitycalc/iter_data.py
permittivitycalc/permittivity_plot.py
permittivitycalc/sparam_data.py
permittivitycalc/data/rexolite_PAL.txt
permittivitycalc/data/serpentine_dry.txt
permittivitycalc/tests/__init__.py
permittivitycalc/tests/test_helper_functions.py
permittivitycalc/tests/test_iter_data.py
permittivitycalc/tests/test_permittivity_plot.py
permittivitycalc/tests/test_sparam_data.py
permittivitycalc-0.6.1.dist-info/LICENSE.txt
permittivitycalc-0.6.1.dist-info/METADATA
permittivitycalc-0.6.1.dist-info/WHEEL
permittivitycalc-0.6.1.dist-info/top_level.txt
permittivitycalc-0.6.1.dist-info/RECORD
