Metadata-Version: 2.1
Name: permittivitycalc
Version: 0.6.1
Summary: Scripts to calculate and plot the complex permittivity from S-parameter data
Home-page: https://github.com/boivinalex/permittivitycalc
Author: Alexandre Boivin
Author-email: alex.boivin@utoronto.ca
License: UNKNOWN
Keywords: python dielectric permittivity s-parameter data analysis
Platform: UNKNOWN
Classifier: Development Status :: 3 - Alpha
Classifier: Intended Audience :: Science/Research
Classifier: Topic :: Scientific/Engineering
Classifier: Natural Language :: English
Classifier: License :: OSI Approved :: MIT License
Classifier: Programming Language :: Python :: 3.6
Classifier: Programming Language :: Python :: 3.7
Requires-Python: >=3.6, <3.8
Requires-Dist: numpy
Requires-Dist: uncertainties
Requires-Dist: matplotlib
Requires-Dist: seaborn
Requires-Dist: cycler
Requires-Dist: scipy
Requires-Dist: lmfit (==0.9.14)
Requires-Dist: emcee (==3.0.2)
Requires-Dist: corner
Requires-Dist: tqdm
